calculatorGS/__init__.py
calculatorGS/calculatorGS.py
calculatorgs-0.4.dist-info/METADATA
calculatorgs-0.4.dist-info/WHEEL
calculatorgs-0.4.dist-info/licenses/LICENSE
calculatorgs-0.4.dist-info/RECORD
