Metadata-Version: 2.1
Name: calculatorGS
Version: 0.4
Summary: A calculator package which performs basic operations.
Author: Gediminas Sumskis
License-File: LICENSE
Classifier: License :: OSI Approved :: MIT License
Classifier: Operating System :: OS Independent
Classifier: Programming Language :: Python :: 3
Requires-Python: >=3.7
